[{"documents": [{"directory": "/home/tony/Downloads/jsn6", "name": "/home/tony/Downloads/img6/111.jpg", "id": "0"}], "annotation": {"id": "0", "version": "2.0", "annotationGroups": [{"id": "0", "annotationEntities": [{"id": "0", "name": "water", "annotationBlocks": [{"id": "0", "settings": {"color": "red", "closed": true}, "segments": [[[639.0, 192.5], [639.0, 358.5], [0.0, 358.5], [0.0, 194.5], [8.0, 193.5], [84.0, 189.5], [281.0, 187.5], [344.0, 187.5], [494.0, 188.5], [628.0, 190.5], [636.0, 191.5]]]}]}]}]}}]